naminter/__init__.py
naminter/cli/__init__.py
naminter/cli/config.py
naminter/cli/console.py
naminter/cli/exporters.py
naminter/cli/main.py
naminter/cli/progress.py
naminter/cli/templates/report.html
naminter/core/__init__.py
naminter/core/constants.py
naminter/core/exceptions.py
naminter/core/main.py
naminter/core/models.py
naminter/core/utils.py
naminter-1.0.6.dist-info/METADATA
naminter-1.0.6.dist-info/WHEEL
naminter-1.0.6.dist-info/entry_points.txt
naminter-1.0.6.dist-info/top_level.txt
naminter-1.0.6.dist-info/RECORD
