Metadata-Version: 2.4
Name: naminter
Version: 1.0.6
Summary: The most powerful and fast username availability checker that searches across hundreds of websites using WhatsMyName dataset
Author-email: 3xp0rt <contact@3xp0rt.com>
Maintainer: 3xp0rt
License: MIT
Project-URL: Homepage, https://github.com/3xp0rt/naminter
Project-URL: Repository, https://github.com/3xp0rt/naminter
Project-URL: BugTracker, https://github.com/3xp0rt/naminter/issues
Project-URL: Documentation, https://github.com/3xp0rt/naminter#readme
Project-URL: Source, https://github.com/3xp0rt/naminter
Keywords: osint,username,availability,checker,whatsmyname,reconnaissance,cybersecurity,investigation,naminter
Classifier: Development Status :: 5 - Production/Stable
Classifier: Environment :: Console
Classifier: Intended Audience :: End Users/Desktop
Classifier: License :: OSI Approved :: MIT License
Classifier: Operating System :: OS Independent
Classifier: Programming Language :: Python :: 3
Classifier: Programming Language :: Python :: 3.8
Classifier: Programming Language :: Python :: 3.9
Classifier: Programming Language :: Python :: 3.10
Classifier: Programming Language :: Python :: 3.11
Classifier: Programming Language :: Python :: 3.12
Classifier: Programming Language :: Python :: 3.13
Classifier: Topic :: Internet
Classifier: Topic :: Utilities
Requires-Python: >=3.8
Requires-Dist: typer>=0.16.0
Requires-Dist: rich>=14.0.0
Requires-Dist: curl-cffi>=0.11.4
Requires-Dist: jsonschema>=4.24.0
Requires-Dist: jinja2>=3.1.6
Requires-Dist: weasyprint>=65.1
